flyteplugins/wandb/__init__.py
flyteplugins/wandb/_context.py
flyteplugins/wandb/_decorator.py
flyteplugins/wandb/_link.py
flyteplugins_wandb-2.0.0b53.dist-info/METADATA
flyteplugins_wandb-2.0.0b53.dist-info/WHEEL
flyteplugins_wandb-2.0.0b53.dist-info/top_level.txt
flyteplugins_wandb-2.0.0b53.dist-info/RECORD
