Metadata-Version: 2.4
Name: flyteplugins-wandb
Version: 2.0.0b53
Summary: Weights & Biases plugin for Flyte
Author: Flyte Contributors
Requires-Python: >=3.10
Requires-Dist: wandb
Requires-Dist: flyte
